[{"rank": 1, "score": 61, "rating": 2614, "username": "Prettyfly", "title": "IM", "performance": 2639, "team": "birman-and-half"}, {"rank": 2, "score": 59, "rating": 2551, "username": "Flo_55", "performance": 2648, "team": "paard-d4"}, {"rank": 3, "score": 55, "rating": 2472, "username": "Atomrod", "title": "GM", "performance": 2549, "team": "english-chess-players"}, {"rank": 4, "score": 51, "rating": 2455, "username": "oferglick", "performance": 2416, "team": "birman-and-half"}, {"rank": 5, "score": 49, "rating": 2495, "username": "Poblesk", "performance": 2547, "team": "eecA2R3b"}, {"rank": 6, "score": 48, "rating": 2506, "username": "Trullebullen", "performance": 2569, "team": "wasa-sk"}, {"rank": 7, "score": 46, "rating": 2332, "username": "Westqz", "performance": 2355, "team": "3eFUgxAM"}, {"rank": 8, "score": 45, "rating": 2216, "username": "BolivarMoises", "performance": 2500, "team": "fundacion-bienestar-club-escuela-caballos-de-caissa"}, {"rank": 9, "score": 44, "rating": 2491, "username": "mokerslag", "performance": 2565, "team": "paard-d4"}, {"rank": 10, "score": 43, "rating": 2500, "username": "kingofspeedd", "performance": 2718, "team": "jLsFRczG"}, {"rank": 11, "score": 43, "rating": 2539, "username": "Cafechess", "performance": 2491, "team": "wasa-sk"}, {"rank": 12, "score": 43, "rating": 2288, "username": "Zakharchuk", "performance": 2481, "team": "eecA2R3b"}, {"rank": 13, "score": 41, "rating": 2597, "username": "vwnv7", "title": "WGM", "performance": 2687, "team": "wasa-sk"}, {"rank": 14, "score": 40, "rating": 2402, "username": "HoseinBitaraf", "performance": 2344, "team": "3eFUgxAM"}, {"rank": 15, "score": 40, "rating": 2324, "username": "SeymourScagneti", "performance": 2322, "team": "birman-and-half"}, {"rank": 16, "score": 38, "rating": 2461, "username": "onyxz", "performance": 2361, "team": "3eFUgxAM"}, {"rank": 17, "score": 37, "rating": 2596, "username": "vvtb", "performance": 2559, "team": "3eFUgxAM"}, {"rank": 18, "score": 37, "rating": 2365, "username": "QuarantaeneSchlumpf", "performance": 2491, "team": "sw-nurnberg-sud"}, {"rank": 19, "score": 37, "rating": 2394, "username": "Belisar603", "title": "FM", "performance": 2212, "team": "sc-weisse-dame-ev"}, {"rank": 20, "score": 36, "rating": 2387, "username": "MaybeOkYess", "performance": 2418, "team": "paard-d4"}, {"rank": 21, "score": 35, "rating": 2377, "username": "gijsijsijs", "performance": 2369, "team": "paard-d4"}, {"rank": 22, "score": 34, "rating": 2388, "username": "The_Knight_of_Spring", "performance": 2460, "team": "english-chess-players"}, {"rank": 23, "score": 34, "rating": 2379, "username": "JeremyDuran", "performance": 2376, "team": "fundacion-bienestar-club-escuela-caballos-de-caissa"}, {"rank": 24, "score": 34, "rating": 2331, "username": "UnoDosChess", "performance": 2347, "team": "birman-and-half"}, {"rank": 25, "score": 32, "rating": 2313, "username": "mohammadreza-s", "performance": 2319, "team": "3eFUgxAM"}, {"rank": 26, "score": 32, "rating": 2178, "username": "Spusak", "performance": 2188, "team": "birman-and-half"}, {"rank": 27, "score": 31, "rating": 2076, "username": "IgorNds", "performance": 2241, "team": "eecA2R3b"}, {"rank": 28, "score": 31, "rating": 2153, "username": "HURACAN_SI", "performance": 2134, "team": "fundacion-bienestar-club-escuela-caballos-de-caissa"}, {"rank": 29, "score": 30, "rating": 2412, "username": "Mkarp", "title": "FM", "performance": 2444, "team": "birman-and-half"}, {"rank": 30, "score": 30, "rating": 2502, "username": "Kevin_Hoegy", "performance": 2390, "team": "sc-weisse-dame-ev"}, {"rank": 31, "score": 30, "rating": 2242, "username": "Klammerer", "performance": 2127, "team": "sw-nurnberg-sud"}, {"rank": 32, "score": 30, "rating": 2161, "username": "Flitze", "performance": 2114, "team": "sc-weisse-dame-ev"}, {"rank": 33, "score": 29, "rating": 2346, "username": "togarasan", "performance": 2431, "team": "sw-nurnberg-sud"}, {"rank": 34, "score": 29, "rating": 2296, "username": "MartinBurrows", "performance": 2368, "team": "english-chess-players"}, {"rank": 35, "score": 29, "rating": 2279, "username": "jeroensch", "performance": 2234, "team": "paard-d4"}, {"rank": 36, "score": 28, "rating": 2511, "username": "Salvaged_Dirt", "performance": 2534, "team": "paard-d4"}, {"rank": 37, "score": 28, "rating": 2334, "username": "jka", "performance": 2262, "team": "sc-weisse-dame-ev"}, {"rank": 38, "score": 28, "rating": 2370, "username": "Murphy_Schlumpf", "performance": 2259, "team": "sw-nurnberg-sud"}, {"rank": 39, "score": 28, "rating": 2361, "username": "danatcramlingdotcom", "performance": 2210, "team": "wasa-sk"}, {"rank": 40, "score": 27, "rating": 1885, "username": "Manin-soltaniii", "performance": 1933, "team": "jLsFRczG"}, {"rank": 41, "score": 27, "rating": 2022, "username": "Desmedido", "performance": 1884, "team": "fundacion-bienestar-club-escuela-caballos-de-caissa"}, {"rank": 42, "score": 26, "rating": 2648, "username": "CheckThis1", "title": "IM", "performance": 2525, "team": "english-chess-players"}, {"rank": 43, "score": 26, "rating": 2312, "username": "farshad_6020", "performance": 2334, "team": "3eFUgxAM"}, {"rank": 44, "score": 26, "rating": 2355, "username": "Boeke", "performance": 2295, "team": "paard-d4"}, {"rank": 45, "score": 26, "rating": 2282, "username": "PlainBobDoubles", "performance": 2194, "team": "english-chess-players"}, {"rank": 46, "score": 25, "rating": 2201, "username": "DaleBCooper", "performance": 2140, "team": "sw-nurnberg-sud"}, {"rank": 47, "score": 24, "rating": 2033, "username": "Bhuvi06", "performance": 2164, "team": "sc-weisse-dame-ev"}, {"rank": 48, "score": 24, "rating": 2154, "username": "WeDaChris", "performance": 2135, "team": "sc-weisse-dame-ev"}, {"rank": 49, "score": 24, "rating": 2160, "username": "mirzaeierfan1385", "performance": 2066, "team": "3eFUgxAM"}, {"rank": 50, "score": 24, "rating": 2041, "username": "Porky74", "performance": 2019, "team": "sw-nurnberg-sud"}, {"rank": 51, "score": 23, "rating": 2264, "username": "Wasanator", "performance": 2301, "team": "wasa-sk"}, {"rank": 52, "score": 23, "rating": 2090, "username": "birjand2016", "performance": 2064, "team": "3eFUgxAM"}, {"rank": 53, "score": 22, "rating": 2253, "username": "mostafa_r", "performance": 2238, "team": "3eFUgxAM"}, {"rank": 54, "score": 22, "rating": 2142, "username": "Schlumpfnochmal", "performance": 2233, "team": "sw-nurnberg-sud"}, {"rank": 55, "score": 22, "rating": 1962, "username": "A_vafaei", "performance": 2019, "team": "3eFUgxAM"}, {"rank": 56, "score": 22, "rating": 1775, "username": "Radin_keyvaninejad", "performance": 1868, "team": "3eFUgxAM"}, {"rank": 57, "score": 21, "rating": 2598, "username": "Maurice93", "title": "FM", "performance": 2391, "team": "paard-d4"}, {"rank": 58, "score": 21, "rating": 2288, "username": "MrXY71", "performance": 2191, "team": "sc-weisse-dame-ev"}, {"rank": 59, "score": 21, "rating": 2277, "username": "Rybchenko", "performance": 2125, "team": "eecA2R3b"}, {"rank": 60, "score": 21, "rating": 2208, "username": "CccLllZzz_15_07_22", "performance": 2042, "team": "sc-weisse-dame-ev"}, {"rank": 61, "score": 20, "rating": 2143, "username": "samh2022", "performance": 2287, "team": "3eFUgxAM"}, {"rank": 62, "score": 20, "rating": 2271, "username": "filmroz", "performance": 2228, "team": "jLsFRczG"}, {"rank": 63, "score": 20, "rating": 2198, "username": "Reali", "performance": 2191, "team": "3eFUgxAM"}, {"rank": 64, "score": 20, "rating": 2145, "username": "Leonid_A", "performance": 2146, "team": "birman-and-half"}, {"rank": 65, "score": 20, "rating": 2270, "username": "DavidWilson1980", "performance": 2058, "team": "english-chess-players"}, {"rank": 66, "score": 19, "rating": 2125, "username": "sygermi", "performance": 2143, "team": "3eFUgxAM"}, {"rank": 67, "score": 19, "rating": 1736, "username": "manch007", "performance": 1801, "team": "english-chess-players"}, {"rank": 68, "score": 18, "rating": 2428, "username": "piscatorox", "title": "CM", "performance": 2356, "team": "english-chess-players"}, {"rank": 69, "score": 18, "rating": 2256, "username": "DieDameIstWeg", "performance": 2146, "team": "sc-weisse-dame-ev"}, {"rank": 70, "score": 18, "rating": 2068, "username": "noamaharoni", "performance": 2137, "team": "birman-and-half"}, {"rank": 71, "score": 18, "rating": 2095, "username": "Bohdan73", "performance": 2088, "team": "eecA2R3b"}, {"rank": 72, "score": 18, "rating": 2069, "username": "CremeFresh13", "performance": 2068, "team": "paard-d4"}, {"rank": 73, "score": 18, "rating": 2060, "username": "kaveh_honari", "performance": 2061, "team": "jLsFRczG"}, {"rank": 74, "score": 17, "rating": 2324, "username": "sherlook1387", "performance": 2407, "team": "3eFUgxAM"}, {"rank": 75, "score": 17, "rating": 2356, "username": "nazriz", "performance": 2380, "team": "english-chess-players"}, {"rank": 76, "score": 17, "rating": 2072, "username": "Henny_Penny", "performance": 2022, "team": "english-chess-players"}, {"rank": 77, "score": 17, "rating": 1959, "username": "LaDamadelTablero", "performance": 1978, "team": "fundacion-bienestar-club-escuela-caballos-de-caissa"}, {"rank": 78, "score": 16, "rating": 1855, "username": "Abolfazl-2007", "performance": 1961, "team": "jLsFRczG"}, {"rank": 79, "score": 16, "rating": 2053, "username": "SpeedyGonzalesWD", "performance": 1916, "team": "sc-weisse-dame-ev"}, {"rank": 80, "score": 15, "rating": 2271, "username": "valyhabibi", "performance": 2154, "team": "3eFUgxAM"}, {"rank": 81, "score": 15, "rating": 2031, "username": "khswampy", "performance": 2083, "team": "english-chess-players"}, {"rank": 82, "score": 15, "rating": 2026, "username": "nigelst", "performance": 1906, "team": "english-chess-players"}, {"rank": 83, "score": 14, "rating": 2480, "username": "sanam2019", "performance": 2567, "team": "fundacion-bienestar-club-escuela-caballos-de-caissa"}, {"rank": 84, "score": 14, "rating": 1885, "username": "ezylevy", "performance": 1820, "team": "birman-and-half"}, {"rank": 85, "score": 14, "rating": 1763, "username": "el_ingenegro", "performance": 1690, "team": "fundacion-bienestar-club-escuela-caballos-de-caissa"}, {"rank": 86, "score": 13, "rating": 2196, "username": "amichaikk", "performance": 2098, "team": "birman-and-half"}, {"rank": 87, "score": 13, "rating": 2274, "username": "Deivisz", "performance": 2013, "team": "fundacion-bienestar-club-escuela-caballos-de-caissa"}, {"rank": 88, "score": 12, "rating": 2346, "username": "ariatalebi", "performance": 2436, "team": "3eFUgxAM"}, {"rank": 89, "score": 12, "rating": 2262, "username": "oliverponte_uah", "performance": 2202, "team": "fundacion-bienestar-club-escuela-caballos-de-caissa"}, {"rank": 90, "score": 12, "rating": 2218, "username": "caballerowil11", "performance": 2007, "team": "fundacion-bienestar-club-escuela-caballos-de-caissa"}, {"rank": 91, "score": 12, "rating": 2059, "username": "Anisahemati4", "performance": 2003, "team": "jLsFRczG"}, {"rank": 92, "score": 12, "rating": 2165, "username": "vleeshhd", "performance": 1940, "team": "english-chess-players"}, {"rank": 93, "score": 12, "rating": 1819, "username": "aylin_whitequeen", "performance": 1833, "team": "sw-nurnberg-sud"}, {"rank": 94, "score": 11, "rating": 2382, "username": "rastinmusapor2004", "performance": 2740, "team": "3eFUgxAM"}, {"rank": 95, "score": 11, "rating": 2312, "username": "Ali_shabanpour_67", "performance": 2255, "team": "3eFUgxAM"}, {"rank": 96, "score": 11, "rating": 1858, "username": "mohema", "performance": 2013, "team": "3eFUgxAM"}, {"rank": 97, "score": 10, "rating": 2159, "username": "honey2010", "performance": 2125, "team": "3eFUgxAM"}, {"rank": 98, "score": 9, "rating": 2221, "username": "GouwenTijden", "performance": 2193, "team": "paard-d4"}, {"rank": 99, "score": 7, "rating": 2112, "username": "Damaso-Isaac", "performance": 2438, "team": "fundacion-bienestar-club-escuela-caballos-de-caissa"}, {"rank": 100, "score": 7, "rating": 2121, "username": "HSV_0502", "performance": 2211, "team": "eecA2R3b"}, {"rank": 101, "score": 7, "rating": 2157, "username": "EdenHazard8", "performance": 1996, "team": "english-chess-players"}, {"rank": 102, "score": 7, "rating": 1825, "username": "Mahdiahmadi007", "performance": 1932, "team": "jLsFRczG"}, {"rank": 103, "score": 6, "rating": 2151, "username": "Tripp-Trapp-Trull", "title": "CM", "performance": 2184, "team": "wasa-sk"}, {"rank": 104, "score": 6, "rating": 2037, "username": "mychess51", "performance": 2153, "team": "english-chess-players"}, {"rank": 105, "score": 5, "rating": 2275, "username": "Arash-bahadorii", "performance": 2308, "team": "jLsFRczG"}, {"rank": 106, "score": 5, "rating": 2269, "username": "Alfredokiller", "performance": 2187, "team": "fundacion-bienestar-club-escuela-caballos-de-caissa"}, {"rank": 107, "score": 5, "rating": 2269, "username": "mohghase", "performance": 2020, "team": "3eFUgxAM"}, {"rank": 108, "score": 5, "rating": 1819, "username": "ZAchess19", "performance": 1728, "team": "english-chess-players"}, {"rank": 109, "score": 5, "rating": 1814, "username": "amiralicarlsen", "performance": 1714, "team": "3eFUgxAM"}, {"rank": 110, "score": 5, "rating": 2021, "username": "jvmaximus", "performance": 1696, "team": "fundacion-bienestar-club-escuela-caballos-de-caissa"}, {"rank": 111, "score": 4, "rating": 2267, "username": "king_chesss", "performance": 2077, "team": "3eFUgxAM"}, {"rank": 112, "score": 4, "rating": 2120, "username": "Harambe07", "performance": 2066, "team": "wasa-sk"}, {"rank": 113, "score": 4, "rating": 1949, "username": "ali201785_3", "performance": 1804, "team": "3eFUgxAM"}, {"rank": 114, "score": 4, "rating": 1718, "username": "pavanisavailable", "performance": 1774, "team": "english-chess-players"}, {"rank": 115, "score": 4, "rating": 1489, "username": "dibsmpuuf", "performance": 1724, "team": "sc-weisse-dame-ev"}, {"rank": 116, "score": 4, "rating": 1827, "username": "Ocelot32", "performance": 1694, "team": "english-chess-players"}, {"rank": 117, "score": 3, "rating": 1759, "username": "Lora1351", "performance": 1803, "team": "jLsFRczG"}, {"rank": 118, "score": 3, "rating": 2112, "username": "Elgaucho", "performance": 1586, "team": "fundacion-bienestar-club-escuela-caballos-de-caissa"}, {"rank": 119, "score": 2, "rating": 2625, "username": "HellersGM", "title": "GM", "performance": 2756, "team": "wasa-sk"}, {"rank": 120, "score": 2, "rating": 2210, "username": "Solocle", "performance": 2694, "team": "english-chess-players"}, {"rank": 121, "score": 2, "rating": 1922, "username": "chess-mohamadali", "performance": 2333, "team": "3eFUgxAM"}, {"rank": 122, "score": 2, "rating": 1932, "username": "RyanWood01", "performance": 2290, "team": "english-chess-players"}, {"rank": 123, "score": 2, "rating": 2593, "username": "testviking", "title": "IM", "performance": 1987, "team": "wasa-sk"}, {"rank": 124, "score": 2, "rating": 1760, "username": "jennson", "performance": 1952, "team": "english-chess-players"}, {"rank": 125, "score": 2, "rating": 2287, "username": "Saijes71", "performance": 1939, "team": "fundacion-bienestar-club-escuela-caballos-de-caissa"}, {"rank": 126, "score": 2, "rating": 1356, "username": "if7_farhang", "performance": 1902, "team": "jLsFRczG"}, {"rank": 127, "score": 2, "rating": 1511, "username": "ail8alipoor007", "performance": 1707, "team": "jLsFRczG"}, {"rank": 128, "score": 2, "rating": 1007, "username": "Keysiii", "performance": 1546, "team": "jLsFRczG"}, {"rank": 129, "score": 1, "rating": 2371, "username": "fakenews1-0", "title": "NM", "performance": 1852, "team": "english-chess-players"}, {"rank": 130, "score": 1, "rating": 1989, "username": "niayesh_mo", "performance": 1819, "team": "3eFUgxAM"}, {"rank": 131, "score": 0, "rating": 2296, "username": "tigranrules", "team": "sc-weisse-dame-ev"}, {"rank": 132, "score": 0, "rating": 2191, "username": "Tiiiiiiiii2021", "performance": 2193, "team": "jLsFRczG"}, {"rank": 133, "score": 0, "rating": 2128, "username": "MAJIDSALIMI", "team": "3eFUgxAM"}, {"rank": 134, "score": 0, "rating": 2027, "username": "rooz50", "team": "3eFUgxAM"}, {"rank": 135, "score": 0, "rating": 2564, "username": "BigAl1", "title": "IM", "performance": 2025, "team": "english-chess-players"}, {"rank": 136, "score": 0, "rating": 1964, "username": "shervin_1390", "performance": 1955, "team": "3eFUgxAM"}, {"rank": 137, "score": 0, "rating": 1953, "username": "Santiago_de_Jesus", "team": "fundacion-bienestar-club-escuela-caballos-de-caissa"}, {"rank": 138, "score": 0, "rating": 1941, "username": "Artupov65", "team": "fundacion-bienestar-club-escuela-caballos-de-caissa"}, {"rank": 139, "score": 0, "rating": 1902, "username": "turk_mianali", "team": "3eFUgxAM"}, {"rank": 140, "score": 0, "rating": 1895, "username": "mehdi_donyavi", "team": "3eFUgxAM"}, {"rank": 141, "score": 0, "rating": 1880, "username": "rozita_ft", "performance": 1887, "team": "3eFUgxAM"}, {"rank": 142, "score": 0, "rating": 2048, "username": "Mischa1980", "performance": 1884, "team": "sw-nurnberg-sud"}, {"rank": 143, "score": 0, "rating": 1364, "username": "Radin-Amigh93", "performance": 1815, "team": "jLsFRczG"}, {"rank": 144, "score": 0, "rating": 2356, "username": "TonyNiccoli", "performance": 1813, "team": "english-chess-players"}, {"rank": 145, "score": 0, "rating": 1790, "username": "ManaureD", "team": "fundacion-bienestar-club-escuela-caballos-de-caissa"}, {"rank": 146, "score": 0, "rating": 1761, "username": "Amphitritesol", "team": "3eFUgxAM"}, {"rank": 147, "score": 0, "rating": 1603, "username": "Tetro3000", "performance": 1737, "team": "jLsFRczG"}, {"rank": 148, "score": 0, "rating": 2020, "username": "Chesstony24", "performance": 1715, "team": "fundacion-bienestar-club-escuela-caballos-de-caissa"}, {"rank": 149, "score": 0, "rating": 1600, "username": "JVGjvg", "performance": 1570, "team": "fundacion-bienestar-club-escuela-caballos-de-caissa"}, {"rank": 150, "score": 0, "rating": 1461, "username": "MPM1388MPM", "performance": 1547, "team": "jLsFRczG"}, {"rank": 151, "score": 0, "rating": 1855, "username": "cjarbeus", "performance": 1526, "team": "wasa-sk"}, {"rank": 152, "score": 0, "rating": 1501, "username": "taha994-499", "team": "3eFUgxAM"}, {"rank": 153, "score": 0, "rating": 1484, "username": "M-GH-2020", "team": "jLsFRczG"}, {"rank": 154, "score": 0, "rating": 1519, "username": "st33", "performance": 1295, "team": "english-chess-players"}, {"rank": 155, "score": 0, "rating": 1840, "username": "PeNgXiAo_ZhU", "performance": 1004, "team": "english-chess-players"}]